devtools_xml_json/__init__.py
devtools_xml_json-1.0.1.dist-info/METADATA
devtools_xml_json-1.0.1.dist-info/WHEEL
devtools_xml_json-1.0.1.dist-info/top_level.txt
devtools_xml_json-1.0.1.dist-info/RECORD
